buslane/__init__.py
buslane/commands.py
buslane/events.py
buslane/utils.py
buslane-0.0.5.dist-info/LICENSE
buslane-0.0.5.dist-info/METADATA
buslane-0.0.5.dist-info/WHEEL
buslane-0.0.5.dist-info/top_level.txt
buslane-0.0.5.dist-info/RECORD
