Metadata-Version: 2.1
Name: buslane
Version: 0.0.5
Summary: UNKNOWN
Home-page: https://github.com/konradhalas/buslane
Author: Konrad Hałas
Author-email: halas.konrad@gmail.com
License: MIT
Platform: UNKNOWN
Classifier: Development Status :: 3 - Alpha
Classifier: Intended Audience :: Developers
Classifier: License :: OSI Approved :: MIT License
Classifier: Operating System :: OS Independent
Classifier: Programming Language :: Python
Classifier: Programming Language :: Python :: 3.6
Classifier: Programming Language :: Python :: 3.7
Classifier: Topic :: Software Development :: Libraries :: Python Modules
Requires-Python: >=3.6
